{
"casuality sequences": [["(K,f0,F)", "(F,g3,G)", "(G,d0,D)", "(D,j4,J)", "(J,l6,L)", "(L,a1,A)", "(A,g0,G)", "(G,c3,C)"], ["(K,f0,F)", "(F,g4,G)", "(G,k2,K)", "(K,i0,I)", "(I,g1,G)", "(G,a1,A)", "(A,h1,H)", "(H,l0,L)"]],
"Non casuality sequences": [],
"states": ["q13", "q4", "q6", "q1", "q9", "q0", "q8", "q10", "q3", "q11", "q14", "q5", "q12", "q2", "q7"],
"initial_state": "q0",
"transitions": {"q0": {"K-f0-F": "q1"},
     "q1": {"F-g3-G": "q2",
     "F-g4-G": "q9"},
     "q2": {"G-d0-D": "q3"},
     "q3": {"D-j4-J": "q4"},
     "q4": {"J-l6-L": "q5"},
     "q5": {"L-a1-A": "q6"},
     "q6": {"A-g0-G": "q7"},
     "q7": {"G-c3-C": "q8"},
     "q8": {},
     "q9": {"G-k2-K": "q10"},
     "q10": {"K-i0-I": "q11"},
     "q11": {"I-g1-G": "q12"},
     "q12": {"G-a1-A": "q13"},
     "q13": {"A-h1-H": "q14"},
     "q14": {"H-l0-L": "q8"}},
"final_states": ["q8"],
"backwards": [],
}
