{
"casuality sequences": [["(E,a3,A)", "(A,c0,C)", "(C,b1,B)"], ["(E,a3,A)", "(A,d1,D)", "(A,b1,B)"], ["(E,a3,A)", "(E,c0,C)", "(C,b1,B)"], ["(E,c1,C)", "(D,a2,A)", "(D,a0,A)"], ["(E,d1,D)", "(E,c0,C)", "(C,b1,B)"]],
"Non casuality sequences": [],
"states": ["q1", "q5", "q7", "q4", "q6", "q2", "q3", "q0"],
"initial_state": "q0",
"transitions": {"q0": {"E-c1-C": "q1",
     "E-a3-A": "q4",
     "E-d1-D": "q7"},
     "q1": {"D-a2-A": "q2"},
     "q2": {"D-a0-A": "q3"},
     "q3": {},
     "q4": {"E-c0-C": "q5",
     "A-c0-C": "q5",
     "A-d1-D": "q6"},
     "q5": {"C-b1-B": "q3"},
     "q6": {"A-b1-B": "q3"},
     "q7": {"E-c0-C": "q5"}},
"final_states": ["q3"],
"backwards": [],
}
